yandex_geocoder/__init__.py
yandex_geocoder/client.py
yandex_geocoder/exceptions.py
yandex_geo-2.1.2.dist-info/LICENSE
yandex_geo-2.1.2.dist-info/METADATA
yandex_geo-2.1.2.dist-info/WHEEL
yandex_geo-2.1.2.dist-info/RECORD
