Metadata-Version: 2.1
Name: yandex-geo
Version: 2.1.2
Summary: Simple library for getting address or coordinates via Yandex geocoder
Home-page: https://github.com/QueGroup/yandex-geocoder
License: MIT
Author: Nikita Sivakov
Author-email: sivakov512@icloud.com
Requires-Python: >=3.11,<4.0
Classifier: License :: OSI Approved :: MIT License
Classifier: Programming Language :: Python :: 3
Classifier: Programming Language :: Python :: 3.11
Classifier: Programming Language :: Python :: 3.12
Requires-Dist: httpx (>=0.27.0,<0.28.0)
Project-URL: Repository, https://github.com/QueGroup/yandex-geocoder
